Metadata-Version: 1.1
Name: compscifirebase
Version: 0.0.1
Summary: Computer Science Firebase Package
Home-page: https://github.com/MrGallen/firebase-compsci
Author: Eoin Gallen
Author-email: egallen@sainteunans.com
License: MIT
Download-URL: https://github.com/MrGallen/firebase-compsci/archive/refs/tags/setup.py.tar.gz
Keywords: pypi,compscifirebase,tutorial
Platform: UNKNOWN
Classifier: Development Status :: 3 - Alpha
Classifier: Intended Audience :: Developers
Classifier: Topic :: Software Development :: Documentation
Classifier: License :: OSI Approved :: MIT License
Classifier: Programming Language :: Python :: 3
Classifier: Programming Language :: Python :: 3.7
Classifier: Programming Language :: Python :: 3.8
Classifier: Programming Language :: Python :: 3.9
